boto3_post_conditions/__init__.py
boto3_post_conditions/enforcer.py
boto3_post_conditions/exceptions.py
boto3_post_conditions/py.typed
boto3_post_conditions/services/__init__.py
boto3_post_conditions/services/secretsmanager.py
boto3_post_conditions/services/ssm.py
boto3_post_conditions-0.3.0.dist-info/WHEEL
boto3_post_conditions-0.3.0.dist-info/METADATA
boto3_post_conditions-0.3.0.dist-info/RECORD
