Metadata-Version: 2.1
Name: boto3-post-conditions
Version: 0.3.0
Summary: Remove retry logic from boto3 clients by enforcing post-conditions.
Home-page: https://github.com/jeking3/boto3-post-conditions/
License: Apache-2.0
Keywords: boto3,aws,eventual consistency,retry
Author: James E. King III
Author-email: jking@apache.org
Requires-Python: >=3.8,<3.11
Classifier: Development Status :: 4 - Beta
Classifier: Intended Audience :: Developers
Classifier: License :: OSI Approved :: Apache Software License
Classifier: Programming Language :: Python :: 3
Classifier: Programming Language :: Python :: 3.10
Classifier: Programming Language :: Python :: 3.8
Classifier: Programming Language :: Python :: 3.9
Classifier: Topic :: Software Development :: Libraries :: Python Modules
Classifier: Typing :: Typed
Requires-Dist: boto3 (>=1.20,<2.0)
Requires-Dist: retry (>=0.9.2,<0.10.0)
Project-URL: Repository, https://github.com/jeking3/boto3-post-conditions/
